{"meta_features": {"is_supervised": true, "has_numeric_features": true, "average_number_of_words": null, "has_categorical_features": false, "semantic_input_types": "(Tensor[2, Continuous, Dense], Supervised[Tensor[1, Categorical, Dense]])", "semantic_output_types": "Tensor[1, Categorical, Dense]", "number_of_samples": 263256, "input_dimensionality": 14, "output_dimensionality": 1, "dataset_dimensionality": 5.318017443097213e-05, "number_of_categorical_features": 0, "number_of_numerical_features": 14, "number_of_missing_values": 0, "standard_deviation": 1.6751259521895865, "coefficient_of_variation": -5.527134056682982, "covariance_avg": 0.07737378380827883, "linear_corr_coef": 0.1460915767897108, "skewness": -0.1528992937911629, "skewness_1": -0.7455476186475483, "skewness_2": 0.212598473143246, "skewness_3": 0.26055545246935413, "kurtosis": null, "normalized_class_entropy": 0.6931441268077038, "normalized_attr_entropy": null, "joint_entropy": null, "mutual_information": null, "equivalent_number_of_attr": null, "noise_signal_ratio": null, "pca": -2.396085063857866, "pca_1": 5.878370530218543}, "meta_labels": {"features": [{"StandardScaler": [1], "RadiusNeighborsTransformer": [1], "MiniBatchKMeans": [1], "End": [1], "StandardScaler_with_mean": [false], "StandardScaler_with_std": [true], "RadiusNeighborsTransformer_mode": [0], "RadiusNeighborsTransformer_radius": [-9.995], "RadiusNeighborsTransformer_algorithm": [2], "RadiusNeighborsTransformer_leaf_size": [6], "RadiusNeighborsTransformer_p": [3], "MiniBatchKMeans_n_clusters": [15], "MiniBatchKMeans_init": [0], "MiniBatchKMeans_compute_labels": [true], "MiniBatchKMeans_tol": [-0.992], "MiniBatchKMeans_max_no_improvement": [1], "MiniBatchKMeans_reassignment_ratio": [0.094]}, {"LogisticRegression": [1], "End": [1], "LogisticRegression_penalty": [1], "LogisticRegression_dual": [true], "LogisticRegression_C": [2.273370542826451], "LogisticRegression_fit_intercept": [false], "LogisticRegression_solver": [0], "LogisticRegression_multi_class": [0]}, {"ComplementNB": [1], "End": [1], "ComplementNB_fit_prior": [false], "ComplementNB_norm": [true]}, {"MeanShift": [1], "End": [1], "MeanShift_bin_seeding": [false], "MeanShift_cluster_all": [false]}, {"TfidfTransformer": [1], "Birch": [1], "End": [1], "TfidfTransformer_norm": [1], "TfidfTransformer_use_idf": [false], "TfidfTransformer_smooth_idf": [false], "TfidfTransformer_sublinear_tf": [true], "Birch_threshold": [3.6162913507117826], "Birch_branching_factor": [95], "Birch_n_clusters": [2], "Birch_compute_labels": [true]}, {"ComplementNB": [1], "End": [1], "ComplementNB_fit_prior": [false], "ComplementNB_norm": [false]}, {"SVC": [1], "End": [1], "SVC_C": [9.991], "SVC_degree": [5], "SVC_gamma": [1], "SVC_coef0": [0.992], "SVC_shrinking": [false], "SVC_probability": [true], "SVC_cache_size": [305], "SVC_decision_function_shape": [0], "SVC_break_ties": [false]}, {"Perceptron": [1], "End": [1], "Perceptron_fit_intercept": [true], "Perceptron_tol": [0.000727858510504077], "Perceptron_shuffle": [false], "Perceptron_eta0": [0.005], "Perceptron_early_stopping": [false], "Perceptron_validation_fraction": [0.006], "Perceptron_n_iter_no_change": [9]}, {"RobustScaler": [1], "ExtraTreeClassifier": [1], "End": [1], "RobustScaler_with_centering": [true], "RobustScaler_with_scaling": [false], "ExtraTreeClassifier_min_samples_split": [3], "ExtraTreeClassifier_min_weight_fraction_leaf": [0.0], "ExtraTreeClassifier_min_impurity_decrease": [0.0], "ExtraTreeClassifier_ccp_alpha": [0.5008190351203409]}, {"AffinityPropagation": [1], "End": [1], "AffinityPropagation_convergence_iter": [5], "AffinityPropagation_affinity": [0]}, {"FactorAnalysis": [1], "MultinomialNB": [1], "End": [1], "FactorAnalysis_tol": [-0.093], "FactorAnalysis_svd_method": [1], "FactorAnalysis_iterated_power": [1], "MultinomialNB_fit_prior": [true]}, {"KNeighborsClassifier": [1], "End": [1], "KNeighborsClassifier_n_neighbors": [1], "KNeighborsClassifier_weights": [1], "KNeighborsClassifier_algorithm": [1], "KNeighborsClassifier_leaf_size": [20], "KNeighborsClassifier_p": [3], "KNeighborsClassifier_metric": [0]}, {"DecisionTreeClassifier": [1], "End": [1], "DecisionTreeClassifier_min_samples_split": [3], "DecisionTreeClassifier_min_weight_fraction_leaf": [0.0], "DecisionTreeClassifier_min_impurity_decrease": [0.9742600809594668], "DecisionTreeClassifier_ccp_alpha": [0.0]}, {"OneClassSVM": [1], "End": [1], "OneClassSVM_kernel": [1], "OneClassSVM_degree": [5], "OneClassSVM_gamma": [1], "OneClassSVM_coef0": [-0.992], "OneClassSVM_shrinking": [true], "OneClassSVM_cache_size": [399]}, {"LogisticRegression": [1], "End": [1], "LogisticRegression_penalty": [0], "LogisticRegression_dual": [false], "LogisticRegression_C": [9.991], "LogisticRegression_fit_intercept": [true], "LogisticRegression_solver": [2], "LogisticRegression_multi_class": [2]}, {"SVC": [1], "End": [1], "SVC_C": [9.991], "SVC_degree": [5], "SVC_gamma": [0], "SVC_coef0": [-0.992], "SVC_shrinking": [false], "SVC_probability": [true], "SVC_cache_size": [399], "SVC_decision_function_shape": [0], "SVC_break_ties": [false]}, {"FeatureAgglomeration": [1], "KNeighborsTransformer": [1], "Perceptron": [1], "End": [1], "FeatureAgglomeration_n_clusters": [1], "FeatureAgglomeration_affinity": [0], "FeatureAgglomeration_compute_full_tree": [0], "FeatureAgglomeration_linkage": [2], "KNeighborsTransformer_mode": [1], "KNeighborsTransformer_n_neighbors": [1], "KNeighborsTransformer_algorithm": [3], "KNeighborsTransformer_leaf_size": [59], "KNeighborsTransformer_p": [2], "Perceptron_fit_intercept": [false], "Perceptron_tol": [0.001], "Perceptron_shuffle": [false], "Perceptron_eta0": [2.8977535645907695], "Perceptron_early_stopping": [false], "Perceptron_validation_fraction": [0.993], "Perceptron_n_iter_no_change": [9]}, {"MultinomialNB": [1], "End": [1], "MultinomialNB_fit_prior": [false]}, {"LocallyLinearEmbedding": [1], "SGDClassifier": [1], "End": [1], "LocallyLinearEmbedding_n_neighbors": [9], "LocallyLinearEmbedding_n_components": [3], "LocallyLinearEmbedding_reg": [-0.0012530585614539758], "LocallyLinearEmbedding_eigen_solver": [0], "LocallyLinearEmbedding_method": [0], "LocallyLinearEmbedding_neighbors_algorithm": [3], "SGDClassifier_loss": [8], "SGDClassifier_penalty": [1], "SGDClassifier_l1_ratio": [0.001], "SGDClassifier_fit_intercept": [true], "SGDClassifier_tol": [0.001], "SGDClassifier_shuffle": [true], "SGDClassifier_epsilon": [0.993], "SGDClassifier_learning_rate": [0], "SGDClassifier_eta0": [0.992], "SGDClassifier_power_t": [0.5546273631609762], "SGDClassifier_early_stopping": [true], "SGDClassifier_validation_fraction": [0.993], "SGDClassifier_n_iter_no_change": [1], "SGDClassifier_average": [true]}, {"SVC": [1], "End": [1], "SVC_C": [0.005], "SVC_degree": [3], "SVC_gamma": [0], "SVC_coef0": [0.8213601257987103], "SVC_shrinking": [true], "SVC_probability": [true], "SVC_cache_size": [1], "SVC_decision_function_shape": [0], "SVC_break_ties": [false]}, {"SGDClassifier": [1], "End": [1], "SGDClassifier_loss": [4], "SGDClassifier_penalty": [2], "SGDClassifier_l1_ratio": [0.001], "SGDClassifier_fit_intercept": [true], "SGDClassifier_tol": [-0.005], "SGDClassifier_shuffle": [true], "SGDClassifier_epsilon": [0.993], "SGDClassifier_learning_rate": [0], "SGDClassifier_eta0": [0.9786906591469855], "SGDClassifier_power_t": [-4.995], "SGDClassifier_early_stopping": [true], "SGDClassifier_validation_fraction": [0.993], "SGDClassifier_n_iter_no_change": [9], "SGDClassifier_average": [true]}, {"MeanShift": [1], "End": [1], "MeanShift_bin_seeding": [true], "MeanShift_cluster_all": [false]}, {"TruncatedSVD": [1], "LinearSVC": [1], "End": [1], "TruncatedSVD_n_components": [2], "TruncatedSVD_n_iter": [1], "TruncatedSVD_tol": [0.992], "LinearSVC_penalty": [0], "LinearSVC_loss": [0], "LinearSVC_dual": [false], "LinearSVC_C": [0.24766391329120196], "LinearSVC_multi_class": [0], "LinearSVC_fit_intercept": [true]}, {"NMF": [1], "DecisionTreeClassifier": [1], "End": [1], "NMF_alpha": [0.0], "NMF_l1_ratio": [0.0], "NMF_shuffle": [true], "DecisionTreeClassifier_min_samples_split": [2], "DecisionTreeClassifier_min_weight_fraction_leaf": [0.0], "DecisionTreeClassifier_min_impurity_decrease": [0.992], "DecisionTreeClassifier_ccp_alpha": [0.992]}, {"LinearSVC": [1], "End": [1], "LinearSVC_penalty": [0], "LinearSVC_loss": [1], "LinearSVC_dual": [true], "LinearSVC_C": [6.86240228086348], "LinearSVC_multi_class": [1], "LinearSVC_fit_intercept": [true]}, {"Isomap": [1], "OneClassSVM": [1], "End": [1], "Isomap_n_neighbors": [1], "Isomap_n_components": [3], "Isomap_eigen_solver": [0], "Isomap_tol": [-99], "Isomap_path_method": [0], "Isomap_neighbors_algorithm": [2], "Isomap_p": [1], "OneClassSVM_kernel": [0], "OneClassSVM_degree": [2], "OneClassSVM_gamma": [0], "OneClassSVM_coef0": [0.992], "OneClassSVM_shrinking": [true], "OneClassSVM_cache_size": [399]}, {"GaussianNB": [1], "End": [1]}, {"LinearSVC": [1], "End": [1], "LinearSVC_penalty": [0], "LinearSVC_loss": [1], "LinearSVC_dual": [true], "LinearSVC_C": [9.991], "LinearSVC_multi_class": [0], "LinearSVC_fit_intercept": [true]}, {"SparsePCA": [1], "GaussianNB": [1], "End": [1], "SparsePCA_ridge_alpha": [-0.093], "SparsePCA_method": [1]}, {"Birch": [1], "End": [1], "Birch_threshold": [4.991], "Birch_branching_factor": [99], "Birch_n_clusters": [1], "Birch_compute_labels": [false]}, {"AffinityPropagation": [1], "End": [1], "AffinityPropagation_convergence_iter": [16], "AffinityPropagation_affinity": [0]}, {"AffinityPropagation": [1], "End": [1], "AffinityPropagation_convergence_iter": [29], "AffinityPropagation_affinity": [0]}, {"MultinomialNB": [1], "End": [1], "MultinomialNB_fit_prior": [false]}, {"GaussianNB": [1], "End": [1]}, {"SVC": [1], "End": [1], "SVC_C": [9.991], "SVC_degree": [1], "SVC_gamma": [1], "SVC_coef0": [0.992], "SVC_shrinking": [false], "SVC_probability": [false], "SVC_cache_size": [1], "SVC_decision_function_shape": [1], "SVC_break_ties": [true]}, {"SVC": [1], "End": [1], "SVC_C": [0.005], "SVC_degree": [3], "SVC_gamma": [1], "SVC_coef0": [-0.7448324254374229], "SVC_shrinking": [true], "SVC_probability": [true], "SVC_cache_size": [1], "SVC_decision_function_shape": [1], "SVC_break_ties": [true]}], "feature_types": [{"StandardScaler": "UnormalizedWeightParam(value=1)", "MiniBatchKMeans": "UnormalizedWeightParam(value=1)", "RadiusNeighborsTransformer": "UnormalizedWeightParam(value=1)", "End": "UnormalizedWeightParam(value=1)", "StandardScaler_with_mean": "WeightParam(value=0.5)", "StandardScaler_with_std": "WeightParam(value=0.5)", "RadiusNeighborsTransformer_mode": "DistributionParam(weights=[0.5, 0.5])", "RadiusNeighborsTransformer_radius": "MeanDevParam(\n    mean=-0.0019999999999997797,\n    dev=19.985999999999997,\n    initial_params=(-0.0019999999999997797, 19.985999999999997),\n)", "RadiusNeighborsTransformer_algorithm": "DistributionParam(weights=[0.25, 0.25, 0.25, 0.25])", "RadiusNeighborsTransformer_leaf_size": "MeanDevParam(mean=30.0, dev=58, initial_params=(30.0, 58))", "RadiusNeighborsTransformer_p": "MeanDevParam(mean=2.0, dev=2, initial_params=(2.0, 2))", "MiniBatchKMeans_n_clusters": "MeanDevParam(mean=8.0, dev=14, initial_params=(8.0, 14))", "MiniBatchKMeans_init": "DistributionParam(weights=[1.0])", "MiniBatchKMeans_compute_labels": "WeightParam(value=0.5)", "MiniBatchKMeans_tol": "MeanDevParam(mean=0.0, dev=1.984, initial_params=(0.0, 1.984))", "MiniBatchKMeans_max_no_improvement": "MeanDevParam(mean=10.0, dev=18, initial_params=(10.0, 18))", "MiniBatchKMeans_reassignment_ratio": "MeanDevParam(\n    mean=0.0005000000000000004, dev=0.187, initial_params=(0.0005000000000000004, 0.187)\n)"}, {"LogisticRegression": "UnormalizedWeightParam(value=1)", "End": "UnormalizedWeightParam(value=1)", "LogisticRegression_penalty": "DistributionParam(weights=[0.5, 0.5])", "LogisticRegression_dual": "WeightParam(value=0.5)", "LogisticRegression_C": "MeanDevParam(\n    mean=4.998, dev=9.985999999999999, initial_params=(4.998, 9.985999999999999)\n)", "LogisticRegression_fit_intercept": "WeightParam(value=0.5)", "LogisticRegression_solver": "DistributionParam(weights=[0.25, 0.25, 0.25, 0.25])", "LogisticRegression_multi_class": "DistributionParam(weights=[0.3333333333333333, 0.3333333333333333, 0.3333333333333333])"}, {"ComplementNB": "UnormalizedWeightParam(value=1)", "End": "UnormalizedWeightParam(value=1)", "ComplementNB_fit_prior": "WeightParam(value=0.5)", "ComplementNB_norm": "WeightParam(value=0.5)"}, {"MeanShift": "UnormalizedWeightParam(value=1)", "End": "UnormalizedWeightParam(value=1)", "MeanShift_bin_seeding": "WeightParam(value=0.5)", "MeanShift_cluster_all": "WeightParam(value=0.5)"}, {"TfidfTransformer": "UnormalizedWeightParam(value=1)", "Birch": "UnormalizedWeightParam(value=1)", "End": "UnormalizedWeightParam(value=1)", "TfidfTransformer_norm": "DistributionParam(weights=[0.5, 0.5])", "TfidfTransformer_use_idf": "WeightParam(value=0.5)", "TfidfTransformer_smooth_idf": "WeightParam(value=0.5)", "TfidfTransformer_sublinear_tf": "WeightParam(value=0.5)", "Birch_threshold": "MeanDevParam(\n    mean=-0.002000000000000224, dev=9.986, initial_params=(-0.002000000000000224, 9.986)\n)", "Birch_branching_factor": "MeanDevParam(mean=50.5, dev=97, initial_params=(50.5, 97))", "Birch_n_clusters": "MeanDevParam(mean=3.0, dev=4, initial_params=(3.0, 4))", "Birch_compute_labels": "WeightParam(value=0.5)"}, {"ComplementNB": "UnormalizedWeightParam(value=1)", "End": "UnormalizedWeightParam(value=1)", "ComplementNB_fit_prior": "WeightParam(value=0.5)", "ComplementNB_norm": "WeightParam(value=0.5)"}, {"SVC": "UnormalizedWeightParam(value=1)", "End": "UnormalizedWeightParam(value=1)", "SVC_C": "MeanDevParam(\n    mean=4.998, dev=9.985999999999999, initial_params=(4.998, 9.985999999999999)\n)", "SVC_degree": "MeanDevParam(mean=3.0, dev=4, initial_params=(3.0, 4))", "SVC_gamma": "DistributionParam(weights=[0.5, 0.5])", "SVC_coef0": "MeanDevParam(mean=0.0, dev=1.984, initial_params=(0.0, 1.984))", "SVC_shrinking": "WeightParam(value=0.5)", "SVC_probability": "WeightParam(value=0.5)", "SVC_cache_size": "MeanDevParam(mean=200.0, dev=398, initial_params=(200.0, 398))", "SVC_decision_function_shape": "DistributionParam(weights=[0.5, 0.5])", "SVC_break_ties": "WeightParam(value=0.5)"}, {"Perceptron": "UnormalizedWeightParam(value=1)", "End": "UnormalizedWeightParam(value=1)", "Perceptron_fit_intercept": "WeightParam(value=0.5)", "Perceptron_tol": "MeanDevParam(mean=-0.002, dev=0.006, initial_params=(-0.002, 0.006))", "Perceptron_shuffle": "WeightParam(value=0.5)", "Perceptron_eta0": "MeanDevParam(\n    mean=4.998, dev=9.985999999999999, initial_params=(4.998, 9.985999999999999)\n)", "Perceptron_early_stopping": "WeightParam(value=0.5)", "Perceptron_validation_fraction": "MeanDevParam(mean=0.4995, dev=0.987, initial_params=(0.4995, 0.987))", "Perceptron_n_iter_no_change": "MeanDevParam(mean=5.0, dev=8, initial_params=(5.0, 8))"}, {"RobustScaler": "UnormalizedWeightParam(value=1)", "ExtraTreeClassifier": "UnormalizedWeightParam(value=1)", "End": "UnormalizedWeightParam(value=1)", "RobustScaler_with_centering": "WeightParam(value=0.5)", "RobustScaler_with_scaling": "WeightParam(value=0.5)", "ExtraTreeClassifier_min_samples_split": "MeanDevParam(mean=2.5, dev=1, initial_params=(2.5, 1))", "ExtraTreeClassifier_min_weight_fraction_leaf": "MeanDevParam(mean=0.25, dev=0.5, initial_params=(0.25, 0.5))", "ExtraTreeClassifier_min_impurity_decrease": "MeanDevParam(mean=0.496, dev=0.992, initial_params=(0.496, 0.992))", "ExtraTreeClassifier_ccp_alpha": "MeanDevParam(mean=0.496, dev=0.992, initial_params=(0.496, 0.992))"}, {"AffinityPropagation": "UnormalizedWeightParam(value=1)", "End": "UnormalizedWeightParam(value=1)", "AffinityPropagation_convergence_iter": "MeanDevParam(mean=15.0, dev=28, initial_params=(15.0, 28))", "AffinityPropagation_affinity": "DistributionParam(weights=[1.0])"}, {"MultinomialNB": "UnormalizedWeightParam(value=1)", "FactorAnalysis": "UnormalizedWeightParam(value=1)", "End": "UnormalizedWeightParam(value=1)", "FactorAnalysis_tol": "MeanDevParam(\n    mean=0.0005000000000000004, dev=0.187, initial_params=(0.0005000000000000004, 0.187)\n)", "FactorAnalysis_svd_method": "DistributionParam(weights=[0.5, 0.5])", "FactorAnalysis_iterated_power": "MeanDevParam(mean=3.0, dev=4, initial_params=(3.0, 4))", "MultinomialNB_fit_prior": "WeightParam(value=0.5)"}, {"KNeighborsClassifier": "UnormalizedWeightParam(value=1)", "End": "UnormalizedWeightParam(value=1)", "KNeighborsClassifier_n_neighbors": "MeanDevParam(mean=5.0, dev=8, initial_params=(5.0, 8))", "KNeighborsClassifier_weights": "DistributionParam(weights=[0.5, 0.5])", "KNeighborsClassifier_algorithm": "DistributionParam(weights=[0.25, 0.25, 0.25, 0.25])", "KNeighborsClassifier_leaf_size": "MeanDevParam(mean=30.0, dev=58, initial_params=(30.0, 58))", "KNeighborsClassifier_p": "MeanDevParam(mean=2.0, dev=2, initial_params=(2.0, 2))", "KNeighborsClassifier_metric": "DistributionParam(weights=[1.0])"}, {"DecisionTreeClassifier": "UnormalizedWeightParam(value=1)", "End": "UnormalizedWeightParam(value=1)", "DecisionTreeClassifier_min_samples_split": "MeanDevParam(mean=2.5, dev=1, initial_params=(2.5, 1))", "DecisionTreeClassifier_min_weight_fraction_leaf": "MeanDevParam(mean=0.25, dev=0.5, initial_params=(0.25, 0.5))", "DecisionTreeClassifier_min_impurity_decrease": "MeanDevParam(mean=0.496, dev=0.992, initial_params=(0.496, 0.992))", "DecisionTreeClassifier_ccp_alpha": "MeanDevParam(mean=0.496, dev=0.992, initial_params=(0.496, 0.992))"}, {"OneClassSVM": "UnormalizedWeightParam(value=1)", "End": "UnormalizedWeightParam(value=1)", "OneClassSVM_kernel": "DistributionParam(weights=[0.25, 0.25, 0.25, 0.25])", "OneClassSVM_degree": "MeanDevParam(mean=3.0, dev=4, initial_params=(3.0, 4))", "OneClassSVM_gamma": "DistributionParam(weights=[0.5, 0.5])", "OneClassSVM_coef0": "MeanDevParam(mean=0.0, dev=1.984, initial_params=(0.0, 1.984))", "OneClassSVM_shrinking": "WeightParam(value=0.5)", "OneClassSVM_cache_size": "MeanDevParam(mean=200.0, dev=398, initial_params=(200.0, 398))"}, {"LogisticRegression": "UnormalizedWeightParam(value=1)", "End": "UnormalizedWeightParam(value=1)", "LogisticRegression_penalty": "DistributionParam(weights=[0.5, 0.5])", "LogisticRegression_dual": "WeightParam(value=0.5)", "LogisticRegression_C": "MeanDevParam(\n    mean=4.998, dev=9.985999999999999, initial_params=(4.998, 9.985999999999999)\n)", "LogisticRegression_fit_intercept": "WeightParam(value=0.5)", "LogisticRegression_solver": "DistributionParam(weights=[0.25, 0.25, 0.25, 0.25])", "LogisticRegression_multi_class": "DistributionParam(weights=[0.3333333333333333, 0.3333333333333333, 0.3333333333333333])"}, {"SVC": "UnormalizedWeightParam(value=1)", "End": "UnormalizedWeightParam(value=1)", "SVC_C": "MeanDevParam(\n    mean=4.998, dev=9.985999999999999, initial_params=(4.998, 9.985999999999999)\n)", "SVC_degree": "MeanDevParam(mean=3.0, dev=4, initial_params=(3.0, 4))", "SVC_gamma": "DistributionParam(weights=[0.5, 0.5])", "SVC_coef0": "MeanDevParam(mean=0.0, dev=1.984, initial_params=(0.0, 1.984))", "SVC_shrinking": "WeightParam(value=0.5)", "SVC_probability": "WeightParam(value=0.5)", "SVC_cache_size": "MeanDevParam(mean=200.0, dev=398, initial_params=(200.0, 398))", "SVC_decision_function_shape": "DistributionParam(weights=[0.5, 0.5])", "SVC_break_ties": "WeightParam(value=0.5)"}, {"Perceptron": "UnormalizedWeightParam(value=1)", "KNeighborsTransformer": "UnormalizedWeightParam(value=1)", "FeatureAgglomeration": "UnormalizedWeightParam(value=1)", "End": "UnormalizedWeightParam(value=1)", "Perceptron_fit_intercept": "WeightParam(value=0.5)", "Perceptron_tol": "MeanDevParam(mean=-0.002, dev=0.006, initial_params=(-0.002, 0.006))", "Perceptron_shuffle": "WeightParam(value=0.5)", "Perceptron_eta0": "MeanDevParam(\n    mean=4.998, dev=9.985999999999999, initial_params=(4.998, 9.985999999999999)\n)", "Perceptron_early_stopping": "WeightParam(value=0.5)", "Perceptron_validation_fraction": "MeanDevParam(mean=0.4995, dev=0.987, initial_params=(0.4995, 0.987))", "Perceptron_n_iter_no_change": "MeanDevParam(mean=5.0, dev=8, initial_params=(5.0, 8))", "FeatureAgglomeration_n_clusters": "MeanDevParam(mean=2.0, dev=2, initial_params=(2.0, 2))", "FeatureAgglomeration_affinity": "DistributionParam(weights=[1.0])", "FeatureAgglomeration_compute_full_tree": "DistributionParam(weights=[1.0])", "FeatureAgglomeration_linkage": "DistributionParam(weights=[0.25, 0.25, 0.25, 0.25])", "KNeighborsTransformer_mode": "DistributionParam(weights=[0.5, 0.5])", "KNeighborsTransformer_n_neighbors": "MeanDevParam(mean=5.0, dev=8, initial_params=(5.0, 8))", "KNeighborsTransformer_algorithm": "DistributionParam(weights=[0.25, 0.25, 0.25, 0.25])", "KNeighborsTransformer_leaf_size": "MeanDevParam(mean=30.0, dev=58, initial_params=(30.0, 58))", "KNeighborsTransformer_p": "MeanDevParam(mean=2.0, dev=2, initial_params=(2.0, 2))"}, {"MultinomialNB": "UnormalizedWeightParam(value=1)", "End": "UnormalizedWeightParam(value=1)", "MultinomialNB_fit_prior": "WeightParam(value=0.5)"}, {"SGDClassifier": "UnormalizedWeightParam(value=1)", "LocallyLinearEmbedding": "UnormalizedWeightParam(value=1)", "End": "UnormalizedWeightParam(value=1)", "LocallyLinearEmbedding_n_neighbors": "MeanDevParam(mean=5.0, dev=8, initial_params=(5.0, 8))", "LocallyLinearEmbedding_n_components": "MeanDevParam(mean=2.0, dev=2, initial_params=(2.0, 2))", "LocallyLinearEmbedding_reg": "MeanDevParam(mean=-0.002, dev=0.006, initial_params=(-0.002, 0.006))", "LocallyLinearEmbedding_eigen_solver": "DistributionParam(weights=[0.3333333333333333, 0.3333333333333333, 0.3333333333333333])", "LocallyLinearEmbedding_method": "DistributionParam(weights=[0.3333333333333333, 0.3333333333333333, 0.3333333333333333])", "LocallyLinearEmbedding_neighbors_algorithm": "DistributionParam(weights=[0.25, 0.25, 0.25, 0.25])", "SGDClassifier_loss": "DistributionParam(\n    weights=[\n        0.1111111111111111,\n        0.1111111111111111,\n        0.1111111111111111,\n        0.1111111111111111,\n        0.1111111111111111,\n        0.1111111111111111,\n        0.1111111111111111,\n        0.1111111111111111,\n        0.1111111111111111,\n    ]\n)", "SGDClassifier_penalty": "DistributionParam(weights=[0.3333333333333333, 0.3333333333333333, 0.3333333333333333])", "SGDClassifier_l1_ratio": "MeanDevParam(mean=0.5, dev=0.998, initial_params=(0.5, 0.998))", "SGDClassifier_fit_intercept": "WeightParam(value=0.5)", "SGDClassifier_tol": "MeanDevParam(mean=-0.002, dev=0.006, initial_params=(-0.002, 0.006))", "SGDClassifier_shuffle": "WeightParam(value=0.5)", "SGDClassifier_epsilon": "MeanDevParam(\n    mean=0.0005000000000000004,\n    dev=1.9849999999999999,\n    initial_params=(0.0005000000000000004, 1.9849999999999999),\n)", "SGDClassifier_learning_rate": "DistributionParam(weights=[1.0])", "SGDClassifier_eta0": "MeanDevParam(mean=0.0, dev=1.984, initial_params=(0.0, 1.984))", "SGDClassifier_power_t": "MeanDevParam(\n    mean=-0.002000000000000224, dev=9.986, initial_params=(-0.002000000000000224, 9.986)\n)", "SGDClassifier_early_stopping": "WeightParam(value=0.5)", "SGDClassifier_validation_fraction": "MeanDevParam(mean=0.4995, dev=0.987, initial_params=(0.4995, 0.987))", "SGDClassifier_n_iter_no_change": "MeanDevParam(mean=5.0, dev=8, initial_params=(5.0, 8))", "SGDClassifier_average": "WeightParam(value=0.5)"}, {"SVC": "UnormalizedWeightParam(value=1)", "End": "UnormalizedWeightParam(value=1)", "SVC_C": "MeanDevParam(\n    mean=4.998, dev=9.985999999999999, initial_params=(4.998, 9.985999999999999)\n)", "SVC_degree": "MeanDevParam(mean=3.0, dev=4, initial_params=(3.0, 4))", "SVC_gamma": "DistributionParam(weights=[0.5, 0.5])", "SVC_coef0": "MeanDevParam(mean=0.0, dev=1.984, initial_params=(0.0, 1.984))", "SVC_shrinking": "WeightParam(value=0.5)", "SVC_probability": "WeightParam(value=0.5)", "SVC_cache_size": "MeanDevParam(mean=200.0, dev=398, initial_params=(200.0, 398))", "SVC_decision_function_shape": "DistributionParam(weights=[0.5, 0.5])", "SVC_break_ties": "WeightParam(value=0.5)"}, {"SGDClassifier": "UnormalizedWeightParam(value=1)", "End": "UnormalizedWeightParam(value=1)", "SGDClassifier_loss": "DistributionParam(\n    weights=[\n        0.1111111111111111,\n        0.1111111111111111,\n        0.1111111111111111,\n        0.1111111111111111,\n        0.1111111111111111,\n        0.1111111111111111,\n        0.1111111111111111,\n        0.1111111111111111,\n        0.1111111111111111,\n    ]\n)", "SGDClassifier_penalty": "DistributionParam(weights=[0.3333333333333333, 0.3333333333333333, 0.3333333333333333])", "SGDClassifier_l1_ratio": "MeanDevParam(mean=0.5, dev=0.998, initial_params=(0.5, 0.998))", "SGDClassifier_fit_intercept": "WeightParam(value=0.5)", "SGDClassifier_tol": "MeanDevParam(mean=-0.002, dev=0.006, initial_params=(-0.002, 0.006))", "SGDClassifier_shuffle": "WeightParam(value=0.5)", "SGDClassifier_epsilon": "MeanDevParam(\n    mean=0.0005000000000000004,\n    dev=1.9849999999999999,\n    initial_params=(0.0005000000000000004, 1.9849999999999999),\n)", "SGDClassifier_learning_rate": "DistributionParam(weights=[1.0])", "SGDClassifier_eta0": "MeanDevParam(mean=0.0, dev=1.984, initial_params=(0.0, 1.984))", "SGDClassifier_power_t": "MeanDevParam(\n    mean=-0.002000000000000224, dev=9.986, initial_params=(-0.002000000000000224, 9.986)\n)", "SGDClassifier_early_stopping": "WeightParam(value=0.5)", "SGDClassifier_validation_fraction": "MeanDevParam(mean=0.4995, dev=0.987, initial_params=(0.4995, 0.987))", "SGDClassifier_n_iter_no_change": "MeanDevParam(mean=5.0, dev=8, initial_params=(5.0, 8))", "SGDClassifier_average": "WeightParam(value=0.5)"}, {"MeanShift": "UnormalizedWeightParam(value=1)", "End": "UnormalizedWeightParam(value=1.2)", "MeanShift_bin_seeding": "WeightParam(value=0.5)", "MeanShift_cluster_all": "WeightParam(value=0.5)"}, {"TruncatedSVD": "UnormalizedWeightParam(value=1)", "LinearSVC": "UnormalizedWeightParam(value=1)", "End": "UnormalizedWeightParam(value=1.2)", "TruncatedSVD_n_components": "MeanDevParam(mean=2.0, dev=2, initial_params=(2.0, 2))", "TruncatedSVD_n_iter": "MeanDevParam(mean=5.0, dev=8, initial_params=(5.0, 8))", "TruncatedSVD_tol": "MeanDevParam(mean=0.0, dev=1.984, initial_params=(0.0, 1.984))", "LinearSVC_penalty": "DistributionParam(weights=[1.0])", "LinearSVC_loss": "DistributionParam(weights=[0.5, 0.5])", "LinearSVC_dual": "WeightParam(value=0.5)", "LinearSVC_C": "MeanDevParam(\n    mean=4.998, dev=9.985999999999999, initial_params=(4.998, 9.985999999999999)\n)", "LinearSVC_multi_class": "DistributionParam(weights=[0.5, 0.5])", "LinearSVC_fit_intercept": "WeightParam(value=0.5)"}, {"DecisionTreeClassifier": "UnormalizedWeightParam(value=1.05)", "NMF": "UnormalizedWeightParam(value=1)", "End": "UnormalizedWeightParam(value=1.2)", "DecisionTreeClassifier_min_samples_split": "MeanDevParam(mean=2.525, dev=0.95, initial_params=(2.5, 1))", "DecisionTreeClassifier_min_weight_fraction_leaf": "MeanDevParam(mean=0.2375, dev=0.475, initial_params=(0.25, 0.5))", "DecisionTreeClassifier_min_impurity_decrease": "MeanDevParam(\n    mean=0.5199130040479732, dev=0.9423999999999999, initial_params=(0.496, 0.992)\n)", "DecisionTreeClassifier_ccp_alpha": "MeanDevParam(\n    mean=0.47119999999999995, dev=0.9423999999999999, initial_params=(0.496, 0.992)\n)", "NMF_alpha": "MeanDevParam(mean=0.0, dev=0.0, initial_params=(0.0, 0.0))", "NMF_l1_ratio": "MeanDevParam(mean=0.0, dev=0.0, initial_params=(0.0, 0.0))", "NMF_shuffle": "WeightParam(value=0.5)"}, {"LinearSVC": "UnormalizedWeightParam(value=1)", "End": "UnormalizedWeightParam(value=1.2)", "LinearSVC_penalty": "DistributionParam(weights=[1.0])", "LinearSVC_loss": "DistributionParam(weights=[0.5, 0.5])", "LinearSVC_dual": "WeightParam(value=0.5)", "LinearSVC_C": "MeanDevParam(\n    mean=4.998, dev=9.985999999999999, initial_params=(4.998, 9.985999999999999)\n)", "LinearSVC_multi_class": "DistributionParam(weights=[0.5, 0.5])", "LinearSVC_fit_intercept": "WeightParam(value=0.5)"}, {"Isomap": "UnormalizedWeightParam(value=1)", "OneClassSVM": "UnormalizedWeightParam(value=1)", "End": "UnormalizedWeightParam(value=1.2)", "OneClassSVM_kernel": "DistributionParam(weights=[0.25, 0.25, 0.25, 0.25])", "OneClassSVM_degree": "MeanDevParam(mean=3.0, dev=4, initial_params=(3.0, 4))", "OneClassSVM_gamma": "DistributionParam(weights=[0.5, 0.5])", "OneClassSVM_coef0": "MeanDevParam(mean=0.0, dev=1.984, initial_params=(0.0, 1.984))", "OneClassSVM_shrinking": "WeightParam(value=0.5)", "OneClassSVM_cache_size": "MeanDevParam(mean=200.0, dev=398, initial_params=(200.0, 398))", "Isomap_n_neighbors": "MeanDevParam(mean=5.0, dev=8, initial_params=(5.0, 8))", "Isomap_n_components": "MeanDevParam(mean=2.0, dev=2, initial_params=(2.0, 2))", "Isomap_eigen_solver": "DistributionParam(weights=[0.3333333333333333, 0.3333333333333333, 0.3333333333333333])", "Isomap_tol": "MeanDevParam(mean=0.0, dev=198, initial_params=(0.0, 198))", "Isomap_path_method": "DistributionParam(weights=[1.0])", "Isomap_neighbors_algorithm": "DistributionParam(weights=[0.25, 0.25, 0.25, 0.25])", "Isomap_p": "MeanDevParam(mean=2.0, dev=2, initial_params=(2.0, 2))"}, {"GaussianNB": "UnormalizedWeightParam(value=1)", "End": "UnormalizedWeightParam(value=1.2)"}, {"LinearSVC": "UnormalizedWeightParam(value=1)", "End": "UnormalizedWeightParam(value=1.2)", "LinearSVC_penalty": "DistributionParam(weights=[1.0])", "LinearSVC_loss": "DistributionParam(weights=[0.5, 0.5])", "LinearSVC_dual": "WeightParam(value=0.5)", "LinearSVC_C": "MeanDevParam(\n    mean=4.998, dev=9.985999999999999, initial_params=(4.998, 9.985999999999999)\n)", "LinearSVC_multi_class": "DistributionParam(weights=[0.5, 0.5])", "LinearSVC_fit_intercept": "WeightParam(value=0.5)"}, {"SparsePCA": "UnormalizedWeightParam(value=1)", "GaussianNB": "UnormalizedWeightParam(value=1)", "End": "UnormalizedWeightParam(value=1.2)", "SparsePCA_ridge_alpha": "MeanDevParam(\n    mean=0.0005000000000000004, dev=0.187, initial_params=(0.0005000000000000004, 0.187)\n)", "SparsePCA_method": "DistributionParam(weights=[0.5, 0.5])"}, {"Birch": "UnormalizedWeightParam(value=1)", "End": "UnormalizedWeightParam(value=1.2)", "Birch_threshold": "MeanDevParam(\n    mean=-0.002000000000000224, dev=9.986, initial_params=(-0.002000000000000224, 9.986)\n)", "Birch_branching_factor": "MeanDevParam(mean=50.5, dev=97, initial_params=(50.5, 97))", "Birch_n_clusters": "MeanDevParam(mean=3.0, dev=4, initial_params=(3.0, 4))", "Birch_compute_labels": "WeightParam(value=0.5)"}, {"AffinityPropagation": "UnormalizedWeightParam(value=1)", "End": "UnormalizedWeightParam(value=1.2)", "AffinityPropagation_convergence_iter": "MeanDevParam(mean=15.0, dev=28, initial_params=(15.0, 28))", "AffinityPropagation_affinity": "DistributionParam(weights=[1.0])"}, {"AffinityPropagation": "UnormalizedWeightParam(value=1)", "End": "UnormalizedWeightParam(value=1.2)", "AffinityPropagation_convergence_iter": "MeanDevParam(mean=15.0, dev=28, initial_params=(15.0, 28))", "AffinityPropagation_affinity": "DistributionParam(weights=[1.0])"}, {"MultinomialNB": "UnormalizedWeightParam(value=1)", "End": "UnormalizedWeightParam(value=1.2)", "MultinomialNB_fit_prior": "WeightParam(value=0.5)"}, {"GaussianNB": "UnormalizedWeightParam(value=1)", "End": "UnormalizedWeightParam(value=1.2)"}, {"SVC": "UnormalizedWeightParam(value=1)", "End": "UnormalizedWeightParam(value=1.2)", "SVC_C": "MeanDevParam(\n    mean=4.998, dev=9.985999999999999, initial_params=(4.998, 9.985999999999999)\n)", "SVC_degree": "MeanDevParam(mean=3.0, dev=4, initial_params=(3.0, 4))", "SVC_gamma": "DistributionParam(weights=[0.5, 0.5])", "SVC_coef0": "MeanDevParam(mean=0.0, dev=1.984, initial_params=(0.0, 1.984))", "SVC_shrinking": "WeightParam(value=0.5)", "SVC_probability": "WeightParam(value=0.5)", "SVC_cache_size": "MeanDevParam(mean=200.0, dev=398, initial_params=(200.0, 398))", "SVC_decision_function_shape": "DistributionParam(weights=[0.5, 0.5])", "SVC_break_ties": "WeightParam(value=0.5)"}, {"SVC": "UnormalizedWeightParam(value=1)", "End": "UnormalizedWeightParam(value=1.2)", "SVC_C": "MeanDevParam(\n    mean=4.998, dev=9.985999999999999, initial_params=(4.998, 9.985999999999999)\n)", "SVC_degree": "MeanDevParam(mean=3.0, dev=4, initial_params=(3.0, 4))", "SVC_gamma": "DistributionParam(weights=[0.5, 0.5])", "SVC_coef0": "MeanDevParam(mean=0.0, dev=1.984, initial_params=(0.0, 1.984))", "SVC_shrinking": "WeightParam(value=0.5)", "SVC_probability": "WeightParam(value=0.5)", "SVC_cache_size": "MeanDevParam(mean=200.0, dev=398, initial_params=(200.0, 398))", "SVC_decision_function_shape": "DistributionParam(weights=[0.5, 0.5])", "SVC_break_ties": "WeightParam(value=0.5)"}]}, "meta_targets": [-Infinity, -Infinity, -Infinity, -Infinity, -Infinity, -Infinity, -Infinity, 0.1018284035656402, 0.09885281604538088, -Infinity, -Infinity, -Infinity, 0.09885281604538088, -Infinity, 0.1063361021069692, -Infinity, 0.09937196110210697, -Infinity, -Infinity, -Infinity, -Infinity, -Infinity, 0.09773855348460292, -Infinity, -Infinity, -Infinity, 0.10487996353322529, -Infinity, -Infinity, -Infinity, -Infinity, -Infinity, -Infinity, 0.10487996353322529, -Infinity, -Infinity]}